OcrReq/Ocr_Req.py
OcrReq/__init__.py
Ocr_Req-0.6.dist-info/LICENSE.txt
Ocr_Req-0.6.dist-info/METADATA
Ocr_Req-0.6.dist-info/WHEEL
Ocr_Req-0.6.dist-info/top_level.txt
Ocr_Req-0.6.dist-info/RECORD
