Metadata-Version: 2.1
Name: Ocr-Req
Version: 0.6
Summary: An example python package
Home-page: UNKNOWN
Author: Vardhani k 
Author-email: vardhanikanamarlapudi@gmail.com
License: MIT
Platform: UNKNOWN
License-File: LICENSE.txt
Requires-Dist: setuptools
Requires-Dist: numpy
Requires-Dist: fitz
Requires-Dist: opencv-python
Requires-Dist: imutils
Requires-Dist: PyMuPDF
Requires-Dist: pdfminer
Requires-Dist: PyPDF2
